patools/__main__.py
patools/excel_styling.py
patools-0.3.0.dist-info/licenses/LICENSE
patools-0.3.0.dist-info/METADATA
patools-0.3.0.dist-info/WHEEL
patools-0.3.0.dist-info/top_level.txt
patools-0.3.0.dist-info/RECORD
