Metadata-Version: 2.4
Name: patools
Version: 0.3.0
Requires-Python: >=3.10
License-File: LICENSE
Requires-Dist: openpyxl>=3.1.5
Requires-Dist: pandas>=2.2.3
Dynamic: license-file
